utils_config/__init__.py
utils_config/test/__init__.py
utils_config/test/utils_config_test.py
Utils_Config-1.0.0.dist-info/LICENSE
Utils_Config-1.0.0.dist-info/METADATA
Utils_Config-1.0.0.dist-info/WHEEL
Utils_Config-1.0.0.dist-info/top_level.txt
Utils_Config-1.0.0.dist-info/RECORD
