Metadata-Version: 2.1
Name: Utils-Config
Version: 1.0.0
Summary: Library to use .json files as configuration objects using namedtuple.
Home-page: https://github.com/yeyeto2788/Utils-Config
Author: Juan Biondi
Author-email: juanernestobiondi@gmail.com
License: MIT
Platform: UNKNOWN
Classifier: License :: OSI Approved :: MIT License
Classifier: Programming Language :: Python
Classifier: Programming Language :: Python :: 3
Classifier: Programming Language :: Python :: 3.5
Requires-Python: >=3.5.0
